LICENSE
README.md
setup.py
TradeTimeSeries.egg-info/PKG-INFO
TradeTimeSeries.egg-info/SOURCES.txt
TradeTimeSeries.egg-info/dependency_links.txt
TradeTimeSeries.egg-info/requires.txt
TradeTimeSeries.egg-info/top_level.txt
tradetimeseries/__init__.py
tradetimeseries/trades.py