Metadata-Version: 2.1
Name: TradeTimeSeries
Version: 0.1.0
Summary: Manage exchange time series.
Home-page: https://github.com/nand0san/TradeTimeSeries
Author: nand0san
Classifier: Programming Language :: Python :: 3
Classifier: License :: OSI Approved :: MIT License
Classifier: Operating System :: OS Independent
Requires-Python: >=3.6
License-File: LICENSE
